examples/__init__.py
examples/add_and_delete_comment.py
examples/context.py
examples/follow_unfollow_account.py
examples/get_account_by_id.py
examples/get_account_by_username.py
examples/get_account_followers.py
examples/get_account_following.py
examples/get_account_medias_by_username.py
examples/get_current_top_medias_by_location_id.py
examples/get_current_top_medias_by_tag_name.py
examples/get_location_by_id.py
examples/get_media_by_code.py
examples/get_media_by_id.py
examples/get_media_by_url.py
examples/get_media_comments.py
examples/get_media_likes.py
examples/get_media_tagged_users.py
examples/get_medias_by_location_id.py
examples/get_medias_by_tag.py
examples/get_medias_from_feed.py
examples/get_stories.py
examples/like_and_unlike_media.py
examples/search_accounts_by_username.py
igramscraper/__init__.py
igramscraper/endpoints.py
igramscraper/helper.py
igramscraper/instagram.py
igramscraper/session_manager.py
igramscraper/exception/__init__.py
igramscraper/exception/instagram_auth_exception.py
igramscraper/exception/instagram_exception.py
igramscraper/exception/instagram_not_found_exception.py
igramscraper/model/__init__.py
igramscraper/model/account.py
igramscraper/model/carousel_media.py
igramscraper/model/comment.py
igramscraper/model/initializer_model.py
igramscraper/model/location.py
igramscraper/model/media.py
igramscraper/model/story.py
igramscraper/model/tag.py
igramscraper/model/user_stories.py
igramscraper/two_step_verification/__init__.py
igramscraper/two_step_verification/console_verification.py
igramscraper/two_step_verification/two_step_verification_abstract_class.py
igramscraper-0.3.2.dist-info/LICENSE
igramscraper-0.3.2.dist-info/METADATA
igramscraper-0.3.2.dist-info/WHEEL
igramscraper-0.3.2.dist-info/top_level.txt
igramscraper-0.3.2.dist-info/RECORD
