Metadata-Version: 2.1
Name: igramscraper
Version: 0.3.2
Summary: scrapes medias, likes, followers, tags and all metadata
Home-page: https://github.com/realsirjoe/instagram-scraper
Author: realsirjoe, leungwaiban
Maintainer: realsirjoe, leungwaiban
License: MIT
Platform: UNKNOWN
Classifier: Development Status :: 4 - Beta
Classifier: Operating System :: OS Independent
Classifier: Intended Audience :: Developers
Classifier: Programming Language :: Python
Classifier: Programming Language :: Python :: 3.6
Classifier: Topic :: Software Development :: Libraries
